mfpandas/__init__.py
mfpandas/dcollect.py
mfpandas/irrdbu00-offsets.json
mfpandas/irrdbu00.py
mfpandas/setropts.py
mfpandas-0.1.5.dist-info/METADATA
mfpandas-0.1.5.dist-info/WHEEL
mfpandas-0.1.5.dist-info/top_level.txt
mfpandas-0.1.5.dist-info/RECORD
